{
  "id": 59490,
  "idMal": 59490,
  "mappings": {
    "mal": 59490,
    "anilist": 179999,
    "anidb": null,
    "kitsu": 49103,
    "simkl": null,
    "tmdb": null,
    "tvdb": null,
    "trakt": null,
    "traktType": null,
    "shikimori": 59490,
    "livechart": 12789,
    "animeplanet": "kaiju-no-8-hoshinas-day-off",
    "anisearch": 19512,
    "notify": "N3CFQYjSR"
  },
  "title": {
    "romaji": "Kaijuu 8-gou: Hoshina no Kyuujitsu",
    "english": "Kaiju No. 8: Hoshina's Day Off",
    "native": "怪獣8号 保科の休日",
    "synonyms": [
      "Kaiju No. 8: A Folga de Hoshina"
    ]
  },
  "type": "Special",
  "source": "Manga",
  "status": "Finished Airing",
  "airing": false,
  "episodeCount": 1,
  "episodeLength": 23,
  "aired": {
    "from": "2025-03-28T00:00:00+00:00",
    "to": "2025-03-28"
  },
  "season": "winter",
  "year": 2025,
  "broadcast": {
    "day": null,
    "time": null,
    "timezone": null
  },
  "nextAiringEpisode": null,
  "rating": "PG-13 - Teens 13 or older",
  "score": {
    "malScore": 6.81,
    "anilistScore": 6.9,
    "kitsuRating": 7.17
  },
  "genres": [
    "Slice of Life",
    "Sci-Fi",
    "Shounen"
  ],
  "studios": [
    "Production I.G"
  ],
  "producers": [],
  "images": {
    "poster": "https://cdn.myanimelist.net/images/anime/1262/146724l.jpg",
    "banner": "https://media.kitsu.app/anime/49103/cover_image/65a9a6ffe7db4fef2a6ce916038b7a57.jpg",
    "color": "#e4ae43"
  },
  "trailer": null,
  "synopsis": "After all the tough training by the Defense Force's Third Division, newcomer Reno Ichikawa notices that he has a day off! He is determined to enjoy it to the fullest, but having gotten used to his daily work routine, he cannot recall what to do with this free time. When Reno discovers that the vice-captain of the Third Division, Soushirou Hoshina, has something planned, he decides to follow him with his comrade Iharu Furuhashi to figure out the secret behind his day off.\n\n[Written by MAL Rewrite]",
  "sequence": [
    {
      "malId": 52588,
      "title": {
        "romaji": "Kaijuu 8-gou",
        "english": "Kaiju No. 8",
        "native": "怪獣８号"
      },
      "image": "https://s4.anilist.co/file/anilistcdn/media/anime/cover/medium/bx153288-25FBfFJzEQ5O.jpg",
      "format": "TV",
      "episodes": 12,
      "seasonYear": 2024,
      "relationType": "PARENT"
    },
    {
      "malId": 59489,
      "title": {
        "romaji": "Kaijuu 8-gou Movie",
        "english": "Kaiju No. 8: Mission Recon",
        "native": "怪獣8号 第1期総集編"
      },
      "image": "https://s4.anilist.co/file/anilistcdn/media/anime/cover/medium/bx179998-2QNb7f6oXGUI.jpg",
      "format": "MOVIE",
      "episodes": 1,
      "seasonYear": 2025,
      "relationType": "PARENT"
    },
    {
      "malId": 63138,
      "title": {
        "romaji": "Kaijuu 8-gou: Narumi no Heijitsu",
        "english": null,
        "native": "怪獣８号 鳴海の平日"
      },
      "image": "https://s4.anilist.co/file/anilistcdn/media/anime/cover/medium/bx204431-5JC0YY6i6ECJ.jpg",
      "format": "SPECIAL",
      "episodes": 1,
      "seasonYear": 2026,
      "relationType": "OTHER"
    }
  ],
  "episodes": {},
  "meta": {
    "lastFetched": "2026-06-30T20:10:48.693Z",
    "sourcesUsed": [
      "jikan",
      "kitsu",
      "anilist",
      "animeapi.my.id",
      "zenshin"
    ],
    "missingSources": [],
    "dataVersion": 1
  }
}
