{
  "id": 59499,
  "idMal": 59499,
  "mappings": {
    "mal": 59499,
    "anilist": 185541,
    "anidb": 18964,
    "kitsu": 49130,
    "simkl": 2629438,
    "tmdb": null,
    "tvdb": null,
    "trakt": null,
    "traktType": null,
    "shikimori": 59499,
    "livechart": 10312,
    "animeplanet": "future-folktales-2nd-season",
    "anisearch": 19608,
    "notify": "27qLMq6SR"
  },
  "title": {
    "romaji": "Asatir 2: Mirai no Mukashibanashi",
    "english": "Future Folktales 2",
    "native": "アサティール2 未来の昔ばなし",
    "synonyms": [
      " أساطير في قادم الزمان 2",
      "Asateer – Future's Folktales 2"
    ]
  },
  "type": "TV",
  "source": "Original",
  "status": "Finished Airing",
  "airing": false,
  "episodeCount": 13,
  "episodeLength": null,
  "aired": {
    "from": "2024-11-03T00:00:00+00:00",
    "to": "2025-02-02T00:00:00+00:00"
  },
  "season": "fall",
  "year": 2024,
  "broadcast": {
    "day": "Sundays",
    "time": "07:00",
    "timezone": "Asia/Tokyo"
  },
  "nextAiringEpisode": null,
  "rating": "PG - Children",
  "score": {
    "malScore": 6.39,
    "anilistScore": null,
    "kitsuRating": null
  },
  "genres": [
    "Adventure"
  ],
  "studios": [
    "Toei Animation",
    "Manga Productions"
  ],
  "producers": [],
  "images": {
    "poster": "https://cdn.myanimelist.net/images/anime/1717/144671l.jpg",
    "banner": null,
    "color": "#5093fe"
  },
  "trailer": null,
  "synopsis": "Sequel to Asatir: Mirai no Mukashi Banashi.",
  "sequence": [
    {
      "malId": 41558,
      "title": {
        "romaji": "Asatir: Mirai no Mukashibanashi",
        "english": "Future Folktales",
        "native": "アサティール 未来の昔ばなし"
      },
      "image": "https://s4.anilist.co/file/anilistcdn/media/anime/cover/medium/bx117096-Ealg1PSeoeqh.jpg",
      "format": "ONA",
      "episodes": 13,
      "seasonYear": 2020,
      "relationType": "PREQUEL"
    }
  ],
  "episodes": {
    "1": {
      "episode": "1",
      "length": "25m",
      "airDate": "2024-11-01",
      "title": {
        "en": "The Night the Wolf Cried"
      },
      "tvdbShowId": null,
      "tvdbId": null,
      "seasonNumber": null,
      "episodeNumber": 1,
      "absoluteEpisodeNumber": null,
      "runtime": null,
      "image": null
    },
    "2": {
      "episode": "2",
      "length": "25m",
      "airDate": "2024-11-08",
      "title": {
        "en": "Naash`s Daughters"
      },
      "tvdbShowId": null,
      "tvdbId": null,
      "seasonNumber": null,
      "episodeNumber": 2,
      "absoluteEpisodeNumber": null,
      "runtime": null,
      "image": null
    },
    "3": {
      "episode": "3",
      "length": "25m",
      "airDate": "2024-11-15",
      "title": {
        "en": "The Nameless Faris"
      },
      "tvdbShowId": null,
      "tvdbId": null,
      "seasonNumber": null,
      "episodeNumber": 3,
      "absoluteEpisodeNumber": null,
      "runtime": null,
      "image": null
    },
    "4": {
      "episode": "4",
      "length": "25m",
      "airDate": "2024-11-22",
      "title": {
        "en": "Jared`s Legend"
      },
      "tvdbShowId": null,
      "tvdbId": null,
      "seasonNumber": null,
      "episodeNumber": 4,
      "absoluteEpisodeNumber": null,
      "runtime": null,
      "image": null
    },
    "5": {
      "episode": "5",
      "length": "25m",
      "airDate": "2024-11-29",
      "title": {
        "en": "Tanbouri`s Shoes"
      },
      "tvdbShowId": null,
      "tvdbId": null,
      "seasonNumber": null,
      "episodeNumber": 5,
      "absoluteEpisodeNumber": null,
      "runtime": null,
      "image": null
    },
    "6": {
      "episode": "6",
      "length": "25m",
      "airDate": "2024-12-06",
      "title": {
        "en": "Poison and Sweetness"
      },
      "tvdbShowId": null,
      "tvdbId": null,
      "seasonNumber": null,
      "episodeNumber": 6,
      "absoluteEpisodeNumber": null,
      "runtime": null,
      "image": null
    },
    "7": {
      "episode": "7",
      "length": "25m",
      "airDate": "2024-12-13",
      "title": {
        "en": "Throw Those Squashes Away and Carry Me!"
      },
      "tvdbShowId": null,
      "tvdbId": null,
      "seasonNumber": null,
      "episodeNumber": 7,
      "absoluteEpisodeNumber": null,
      "runtime": null,
      "image": null
    },
    "8": {
      "episode": "8",
      "length": "25m",
      "airDate": "2024-12-20",
      "title": {
        "en": "Iyas the Judge"
      },
      "tvdbShowId": null,
      "tvdbId": null,
      "seasonNumber": null,
      "episodeNumber": 8,
      "absoluteEpisodeNumber": null,
      "runtime": null,
      "image": null
    },
    "9": {
      "episode": "9",
      "length": "25m",
      "airDate": "2024-12-27",
      "title": {
        "en": "Mulukhiyah Wars"
      },
      "tvdbShowId": null,
      "tvdbId": null,
      "seasonNumber": null,
      "episodeNumber": 9,
      "absoluteEpisodeNumber": null,
      "runtime": null,
      "image": null
    },
    "10": {
      "episode": "10",
      "length": "25m",
      "airDate": "2025-01-03",
      "title": {
        "en": "Nafla and Nahla"
      },
      "tvdbShowId": null,
      "tvdbId": null,
      "seasonNumber": null,
      "episodeNumber": 10,
      "absoluteEpisodeNumber": null,
      "runtime": null,
      "image": null
    },
    "11": {
      "episode": "11",
      "length": "25m",
      "airDate": "2025-01-10",
      "title": {
        "en": "The Old Lady and the Jinni"
      },
      "tvdbShowId": null,
      "tvdbId": null,
      "seasonNumber": null,
      "episodeNumber": 11,
      "absoluteEpisodeNumber": null,
      "runtime": null,
      "image": null
    },
    "12": {
      "episode": "12",
      "length": "25m",
      "airDate": "2025-01-17",
      "title": {
        "en": "The Mermaid`s Gifts"
      },
      "tvdbShowId": null,
      "tvdbId": null,
      "seasonNumber": null,
      "episodeNumber": 12,
      "absoluteEpisodeNumber": null,
      "runtime": null,
      "image": null
    },
    "13": {
      "episode": "13",
      "length": "25m",
      "airDate": "2025-01-24",
      "title": {
        "en": "Stories Are Our Treasures"
      },
      "tvdbShowId": null,
      "tvdbId": null,
      "seasonNumber": null,
      "episodeNumber": 13,
      "absoluteEpisodeNumber": null,
      "runtime": null,
      "image": null
    }
  },
  "meta": {
    "lastFetched": "2026-06-30T20:10:57.496Z",
    "sourcesUsed": [
      "jikan",
      "kitsu",
      "anilist",
      "animeapi.my.id",
      "zenshin"
    ],
    "missingSources": [],
    "dataVersion": 1
  }
}
