{
  "id": 4454,
  "idMal": 4454,
  "mappings": {
    "mal": 4454,
    "anilist": 4454,
    "anidb": null,
    "kitsu": 3616,
    "simkl": null,
    "tmdb": null,
    "tvdb": null,
    "trakt": null,
    "traktType": null,
    "shikimori": 4454,
    "livechart": 4917,
    "animeplanet": "macross-frontier-deculture-edition",
    "anisearch": null,
    "notify": "mTwXcKmmg"
  },
  "title": {
    "romaji": "Macross Frontier Deculture Edition",
    "english": null,
    "native": "マクロスＦ",
    "synonyms": [
      "Macross Frontier: Close Encounter - Deculture Edition"
    ]
  },
  "type": "Special",
  "source": "Original",
  "status": "Finished Airing",
  "airing": false,
  "episodeCount": 1,
  "episodeLength": 27,
  "aired": {
    "from": "2007-12-23T00:00:00+00:00",
    "to": "2007-12-23"
  },
  "season": "fall",
  "year": 2007,
  "broadcast": {
    "day": null,
    "time": null,
    "timezone": null
  },
  "nextAiringEpisode": null,
  "rating": "PG-13 - Teens 13 or older",
  "score": {
    "malScore": 7.66,
    "anilistScore": 7.2,
    "kitsuRating": 7.62
  },
  "genres": [
    "Sci-Fi",
    "Action",
    "Mecha",
    "Music",
    "Space",
    "Military",
    "Science Fiction"
  ],
  "studios": [
    "Satelight"
  ],
  "producers": [],
  "images": {
    "poster": "https://cdn.myanimelist.net/images/anime/4/8507l.jpg",
    "banner": null,
    "color": "#93e4bb"
  },
  "trailer": null,
  "synopsis": "An expanded version of the first episode of Macross Frontier.",
  "sequence": [
    {
      "malId": 3572,
      "title": {
        "romaji": "Macross Frontier",
        "english": "Macross Frontier",
        "native": "マクロスF"
      },
      "image": "https://s4.anilist.co/file/anilistcdn/media/anime/cover/medium/bx3572-qYJhokKdsnZR.png",
      "format": "TV",
      "episodes": 25,
      "seasonYear": 2008,
      "relationType": "ALTERNATIVE"
    }
  ],
  "episodes": {},
  "meta": {
    "lastFetched": "2026-06-26T22:38:11.181Z",
    "sourcesUsed": [
      "jikan",
      "kitsu",
      "anilist",
      "animeapi.my.id",
      "zenshin"
    ],
    "missingSources": [],
    "dataVersion": 1
  }
}
