{
  "id": 43349,
  "idMal": 43349,
  "mappings": {
    "mal": 43349,
    "anilist": null,
    "anidb": null,
    "kitsu": 43715,
    "simkl": null,
    "tmdb": null,
    "tvdb": null,
    "trakt": null,
    "traktType": null,
    "shikimori": 43349,
    "livechart": null,
    "animeplanet": "snickers-x-dr-stone-sekikashita-kusanagi",
    "anisearch": 15630,
    "notify": null
  },
  "title": {
    "romaji": "Sekikashita Kusanagi",
    "english": "Snickers x Dr. Stone",
    "native": "石化した草薙",
    "synonyms": [
      "Petrified Kusanagi"
    ]
  },
  "type": "CM",
  "source": "Original",
  "status": "Finished Airing",
  "airing": false,
  "episodeCount": 1,
  "episodeLength": 0,
  "aired": {
    "from": "2020-10-04T00:00:00+00:00",
    "to": "2020-10-04"
  },
  "season": null,
  "year": null,
  "broadcast": {
    "day": null,
    "time": null,
    "timezone": null
  },
  "nextAiringEpisode": null,
  "rating": "G - All Ages",
  "score": {
    "malScore": 7.18,
    "anilistScore": null,
    "kitsuRating": 7.09
  },
  "genres": [
    "Comedy",
    "Shounen",
    "Science Fiction"
  ],
  "studios": [
    "TMS Entertainment"
  ],
  "producers": [],
  "images": {
    "poster": "https://cdn.myanimelist.net/images/anime/1170/111193l.jpg",
    "banner": null,
    "color": null
  },
  "trailer": null,
  "synopsis": "In Sekikashita Kusanagi, Senkuu discovers an alternative way to revive petrified people–using Snickers! By feeding this chocolate to someone who has been petrified, that person will instantly revive just to have a taste of a Snickers bar. With this discovery, Senkuu uses Snickers to revive the famous comedian Kouki Kusanagi. \n\n[Written by MAL Rewrite]",
  "sequence": [],
  "episodes": {},
  "meta": {
    "lastFetched": "2026-06-30T14:07:29.391Z",
    "sourcesUsed": [
      "jikan",
      "kitsu",
      "animeapi.my.id",
      "zenshin"
    ],
    "missingSources": [
      "anilist (not in ID mappings)",
      "episodes (no data from Zenshin or Jikan)"
    ],
    "dataVersion": 1
  }
}
