{
  "id": 2904,
  "idMal": 2904,
  "mappings": {
    "mal": 2904,
    "anilist": 2904,
    "anidb": 5373,
    "kitsu": 2634,
    "simkl": 41541,
    "tmdb": 31724,
    "tvdb": 79525,
    "trakt": 31586,
    "traktType": "shows",
    "shikimori": 2904,
    "livechart": 3584,
    "animeplanet": "code-geass-lelouch-of-the-rebellion-r2",
    "anisearch": 4174,
    "notify": "SGcU5Kiig"
  },
  "title": {
    "romaji": "Code Geass: Hangyaku no Lelouch R2",
    "english": "Code Geass: Lelouch of the Rebellion R2",
    "native": "コードギアス 反逆のルルーシュ R2",
    "synonyms": [
      "Code Geass: Hangyaku no Lelouch 2nd Season",
      "Code Geass: Hangyaku no Lelouch Second Season"
    ]
  },
  "type": "TV",
  "source": "Original",
  "status": "Finished Airing",
  "airing": false,
  "episodeCount": 25,
  "episodeLength": 24,
  "aired": {
    "from": "2008-04-06T00:00:00+00:00",
    "to": "2008-09-28T00:00:00+00:00"
  },
  "season": "spring",
  "year": 2008,
  "broadcast": {
    "day": "Sundays",
    "time": "17:00",
    "timezone": "Asia/Tokyo"
  },
  "nextAiringEpisode": null,
  "rating": "R - 17+ (violence & profanity)",
  "score": {
    "malScore": 8.92,
    "anilistScore": 8.7,
    "kitsuRating": 8.23
  },
  "genres": [
    "Award Winning",
    "Drama",
    "Sci-Fi",
    "Action",
    "Mecha",
    "Thriller",
    "Super Power",
    "Military",
    "Political",
    "Earth",
    "Science Fiction",
    "China",
    "Japan",
    "Asia",
    "Piloted Robot",
    "War",
    "Future",
    "Alternative Present",
    "Politics",
    "Plot Continuity",
    "Present"
  ],
  "studios": [
    "Sunrise"
  ],
  "producers": [
    "Bandai Visual",
    "Mainichi Broadcasting System",
    "Bandai",
    "Bandai Namco Entertainment",
    "Hakuhodo DY Media Partners"
  ],
  "images": {
    "poster": "https://cdn.myanimelist.net/images/anime/1088/135089l.jpg",
    "banner": "https://s4.anilist.co/file/anilistcdn/media/anime/banner/2904-X71fcvE83n3s.jpg",
    "color": "#e4bb50"
  },
  "trailer": null,
  "synopsis": "One year has passed since the Black Rebellion, a failed uprising against the Holy Britannian Empire led by the masked vigilante Zero, who is now missing. At a loss without their revolutionary leader, Area 11's resistance group—the Black Knights—find themselves too powerless to combat the brutality inflicted upon the Elevens by Britannia, which has increased significantly in order to crush any hope of a future revolt. \n\nLelouch Lamperouge, having lost all memory of his double life, is living peacefully alongside his friends as a high school student at Ashford Academy. His former partner C.C., unable to accept this turn of events, takes it upon herself to remind him of his past purpose, hoping that the mastermind Zero will rise once again to finish what he started.\n\n[Written by MAL Rewrite]",
  "sequence": [
    {
      "malId": 1575,
      "title": {
        "romaji": "Code Geass: Hangyaku no Lelouch",
        "english": "Code Geass: Lelouch of the Rebellion",
        "native": "コードギアス 反逆のルルーシュ"
      },
      "image": "https://s4.anilist.co/file/anilistcdn/media/anime/cover/medium/bx1575-hsmWM2ydNm1m.jpg",
      "format": "TV",
      "episodes": 25,
      "seasonYear": 2006,
      "relationType": "PREQUEL"
    },
    {
      "malId": 5163,
      "title": {
        "romaji": "Code Geass: Hangyaku no Lelouch R2 Picture Drama",
        "english": null,
        "native": "コードギアス 反逆のルルーシュ 続編 ピクチャードラマ"
      },
      "image": "https://s4.anilist.co/file/anilistcdn/media/anime/cover/medium/5163.jpg",
      "format": "SPECIAL",
      "episodes": 9,
      "seasonYear": 2008,
      "relationType": "SIDE_STORY"
    },
    {
      "malId": 9591,
      "title": {
        "romaji": "Code Geass: Hangyaku no Lelouch R2 FLASH Flash - Kaette Kita BABA Gekijou",
        "english": "Code Geass: Lelouch of the Rebellion R2: Flash Specials",
        "native": "コードギアス 反逆のルルーシュ おまけFLASH「帰ってきたBABA劇場」"
      },
      "image": "https://s4.anilist.co/file/anilistcdn/media/anime/cover/medium/9591.jpg",
      "format": "SPECIAL",
      "episodes": 9,
      "seasonYear": 2008,
      "relationType": "SIDE_STORY"
    },
    {
      "malId": 8728,
      "title": {
        "romaji": "Code Geass: Hangyaku no Lelouch - Kiseki no Birthday Picture Drama",
        "english": null,
        "native": "コードギアス 反逆のルルーシュ キセキの誕生日 ピクチャードラマ"
      },
      "image": "https://s4.anilist.co/file/anilistcdn/media/anime/cover/medium/8728.jpg",
      "format": "SPECIAL",
      "episodes": 1,
      "seasonYear": 2010,
      "relationType": "SIDE_STORY"
    },
    {
      "malId": 12685,
      "title": {
        "romaji": "Code Geass: Nunnally in Wonderland",
        "english": "Code Geass: Nunnally in Wonderland",
        "native": "コードギアス｜ナナリーinワンダーランド"
      },
      "image": "https://s4.anilist.co/file/anilistcdn/media/anime/cover/medium/bx12685-IfZqKrKbkb1p.png",
      "format": "OVA",
      "episodes": 1,
      "seasonYear": 2012,
      "relationType": "OTHER"
    },
    {
      "malId": 33156,
      "title": {
        "romaji": "Code Geass: Hangyaku no Lelouch R2 Picture Drama TURN 12.06 - Last Moratorium",
        "english": null,
        "native": "コードギアス 反逆のルルーシュ 続編 ピクチャードラマ TURN 12.06 ラストモラトリアム"
      },
      "image": "https://s4.anilist.co/file/anilistcdn/media/anime/cover/medium/b132317-pcgaBGS3O5Dj.jpg",
      "format": "SPECIAL",
      "episodes": 1,
      "seasonYear": null,
      "relationType": "SIDE_STORY"
    },
    {
      "malId": 40334,
      "title": {
        "romaji": "Code Geass: Hangyaku no Lelouch Picture Drama - Kiseki no Anniversary",
        "english": null,
        "native": "コードギアス 反逆のルルーシュ キセキのアニバーサリー"
      },
      "image": "https://s4.anilist.co/file/anilistcdn/media/anime/cover/medium/b112900-w58lVXgdLx93.jpg",
      "format": "SPECIAL",
      "episodes": 1,
      "seasonYear": 2017,
      "relationType": "SIDE_STORY"
    },
    {
      "malId": 34437,
      "title": {
        "romaji": "Code Geass: Fukkatsu no Lelouch",
        "english": "Code Geass: Lelouch of the Re;surrection",
        "native": "コードギアス 復活のルルーシュ"
      },
      "image": "https://s4.anilist.co/file/anilistcdn/media/anime/cover/medium/bx97880-sZWHViJfrvXm.jpg",
      "format": "MOVIE",
      "episodes": 1,
      "seasonYear": 2019,
      "relationType": "OTHER"
    }
  ],
  "episodes": {
    "1": {
      "episode": "1",
      "length": "25m",
      "airDate": "2008-04-06",
      "title": {
        "en": "The Day a Demon Awakens"
      },
      "tvdbShowId": 79525,
      "tvdbId": 359905,
      "seasonNumber": 2,
      "episodeNumber": 1,
      "absoluteEpisodeNumber": 27,
      "runtime": 25,
      "image": "https://artworks.thetvdb.com/banners/episodes/79525/359905.jpg"
    },
    "2": {
      "episode": "2",
      "length": "25m",
      "airDate": "2008-04-13",
      "title": {
        "en": "Plan for Independent Japan"
      },
      "tvdbShowId": 79525,
      "tvdbId": 359925,
      "seasonNumber": 2,
      "episodeNumber": 2,
      "absoluteEpisodeNumber": 28,
      "runtime": 25,
      "image": "https://artworks.thetvdb.com/banners/episodes/79525/359925.jpg"
    },
    "3": {
      "episode": "3",
      "length": "25m",
      "airDate": "2008-04-20",
      "title": {
        "en": "Imprisoned in Campus"
      },
      "tvdbShowId": 79525,
      "tvdbId": 359926,
      "seasonNumber": 2,
      "episodeNumber": 3,
      "absoluteEpisodeNumber": 29,
      "runtime": 25,
      "image": "https://artworks.thetvdb.com/banners/episodes/79525/359926.jpg"
    },
    "4": {
      "episode": "4",
      "length": "25m",
      "airDate": "2008-04-27",
      "title": {
        "en": "Counterattack at the Gallows"
      },
      "tvdbShowId": 79525,
      "tvdbId": 359927,
      "seasonNumber": 2,
      "episodeNumber": 4,
      "absoluteEpisodeNumber": 30,
      "runtime": 25,
      "image": "https://artworks.thetvdb.com/banners/episodes/79525/359927.jpg"
    },
    "5": {
      "episode": "5",
      "length": "25m",
      "airDate": "2008-05-04",
      "title": {
        "en": "Knights of the Round"
      },
      "tvdbShowId": 79525,
      "tvdbId": 363096,
      "seasonNumber": 2,
      "episodeNumber": 5,
      "absoluteEpisodeNumber": 31,
      "runtime": 25,
      "image": "https://artworks.thetvdb.com/banners/episodes/79525/363096.jpg"
    },
    "6": {
      "episode": "6",
      "length": "25m",
      "airDate": "2008-05-11",
      "title": {
        "en": "Surprise Attack over the Pacific"
      },
      "tvdbShowId": 79525,
      "tvdbId": 365978,
      "seasonNumber": 2,
      "episodeNumber": 6,
      "absoluteEpisodeNumber": 32,
      "runtime": 25,
      "image": "https://artworks.thetvdb.com/banners/episodes/79525/365978.jpg"
    },
    "7": {
      "episode": "7",
      "length": "25m",
      "airDate": "2008-05-18",
      "title": {
        "en": "The Abandoned Mask"
      },
      "tvdbShowId": 79525,
      "tvdbId": 367017,
      "seasonNumber": 2,
      "episodeNumber": 7,
      "absoluteEpisodeNumber": 33,
      "runtime": 25,
      "image": "https://artworks.thetvdb.com/banners/episodes/79525/367017.jpg"
    },
    "8": {
      "episode": "8",
      "length": "25m",
      "airDate": "2008-05-25",
      "title": {
        "en": "One Million Miracles"
      },
      "tvdbShowId": 79525,
      "tvdbId": 368023,
      "seasonNumber": 2,
      "episodeNumber": 8,
      "absoluteEpisodeNumber": 34,
      "runtime": 25,
      "image": "https://artworks.thetvdb.com/banners/episodes/79525/368023.jpg"
    },
    "9": {
      "episode": "9",
      "length": "25m",
      "airDate": "2008-06-08",
      "title": {
        "en": "A Bride in the Vermilion Forbidden City"
      },
      "tvdbShowId": 79525,
      "tvdbId": 368835,
      "seasonNumber": 2,
      "episodeNumber": 9,
      "absoluteEpisodeNumber": 35,
      "runtime": 25,
      "image": "https://artworks.thetvdb.com/banners/episodes/79525/368835.jpg"
    },
    "10": {
      "episode": "10",
      "length": "25m",
      "airDate": "2008-06-15",
      "title": {
        "en": "When Shen Hu Wins Glory"
      },
      "tvdbShowId": 79525,
      "tvdbId": 368836,
      "seasonNumber": 2,
      "episodeNumber": 10,
      "absoluteEpisodeNumber": 36,
      "runtime": 25,
      "image": "https://artworks.thetvdb.com/banners/episodes/79525/368836.jpg"
    },
    "11": {
      "episode": "11",
      "length": "25m",
      "airDate": "2008-06-22",
      "title": {
        "en": "Power of Passion"
      },
      "tvdbShowId": 79525,
      "tvdbId": 368837,
      "seasonNumber": 2,
      "episodeNumber": 11,
      "absoluteEpisodeNumber": 37,
      "runtime": 25,
      "image": "https://artworks.thetvdb.com/banners/episodes/79525/368837.jpg"
    },
    "12": {
      "episode": "12",
      "length": "25m",
      "airDate": "2008-06-29",
      "title": {
        "en": "Love Attack!"
      },
      "tvdbShowId": 79525,
      "tvdbId": 368838,
      "seasonNumber": 2,
      "episodeNumber": 12,
      "absoluteEpisodeNumber": 38,
      "runtime": 25,
      "image": "https://artworks.thetvdb.com/banners/episodes/79525/368838.jpg"
    },
    "13": {
      "episode": "13",
      "length": "25m",
      "airDate": "2008-07-06",
      "title": {
        "en": "Assassin from the Past"
      },
      "tvdbShowId": 79525,
      "tvdbId": 372478,
      "seasonNumber": 2,
      "episodeNumber": 13,
      "absoluteEpisodeNumber": 39,
      "runtime": 25,
      "image": "https://artworks.thetvdb.com/banners/episodes/79525/372478.jpg"
    },
    "14": {
      "episode": "14",
      "length": "25m",
      "airDate": "2008-07-13",
      "title": {
        "en": "Geass Hunt"
      },
      "tvdbShowId": 79525,
      "tvdbId": 372479,
      "seasonNumber": 2,
      "episodeNumber": 14,
      "absoluteEpisodeNumber": 40,
      "runtime": 25,
      "image": "https://artworks.thetvdb.com/banners/episodes/79525/372479.jpg"
    },
    "15": {
      "episode": "15",
      "length": "25m",
      "airDate": "2008-07-20",
      "title": {
        "en": "The Cs` World"
      },
      "tvdbShowId": 79525,
      "tvdbId": 374718,
      "seasonNumber": 2,
      "episodeNumber": 15,
      "absoluteEpisodeNumber": 41,
      "runtime": 25,
      "image": "https://artworks.thetvdb.com/banners/episodes/79525/374718.jpg"
    },
    "16": {
      "episode": "16",
      "length": "25m",
      "airDate": "2008-07-27",
      "title": {
        "en": "United Federation of Nations Resolution Number One"
      },
      "tvdbShowId": 79525,
      "tvdbId": 374719,
      "seasonNumber": 2,
      "episodeNumber": 16,
      "absoluteEpisodeNumber": 42,
      "runtime": 25,
      "image": "https://artworks.thetvdb.com/banners/episodes/79525/374719.jpg"
    },
    "17": {
      "episode": "17",
      "length": "25m",
      "airDate": "2008-08-03",
      "title": {
        "en": "The Taste of Humiliation"
      },
      "tvdbShowId": 79525,
      "tvdbId": 374720,
      "seasonNumber": 2,
      "episodeNumber": 17,
      "absoluteEpisodeNumber": 43,
      "runtime": 25,
      "image": "https://artworks.thetvdb.com/banners/episodes/79525/374720.jpg"
    },
    "18": {
      "episode": "18",
      "length": "25m",
      "airDate": "2008-08-10",
      "title": {
        "en": "Final Battle Tokyo II"
      },
      "tvdbShowId": 79525,
      "tvdbId": 379408,
      "seasonNumber": 2,
      "episodeNumber": 18,
      "absoluteEpisodeNumber": 44,
      "runtime": 25,
      "image": "https://artworks.thetvdb.com/banners/episodes/79525/379408.jpg"
    },
    "19": {
      "episode": "19",
      "length": "25m",
      "airDate": "2008-08-17",
      "title": {
        "en": "Betrayal"
      },
      "tvdbShowId": 79525,
      "tvdbId": 379409,
      "seasonNumber": 2,
      "episodeNumber": 19,
      "absoluteEpisodeNumber": 45,
      "runtime": 25,
      "image": "https://artworks.thetvdb.com/banners/episodes/79525/379409.jpg"
    },
    "20": {
      "episode": "20",
      "length": "25m",
      "airDate": "2008-08-24",
      "title": {
        "en": "Emperor Dismissed"
      },
      "tvdbShowId": 79525,
      "tvdbId": 379410,
      "seasonNumber": 2,
      "episodeNumber": 20,
      "absoluteEpisodeNumber": 46,
      "runtime": 25,
      "image": "https://artworks.thetvdb.com/banners/episodes/79525/379410.jpg"
    },
    "21": {
      "episode": "21",
      "length": "25m",
      "airDate": "2008-08-31",
      "title": {
        "en": "The Ragnarok Connection"
      },
      "tvdbShowId": 79525,
      "tvdbId": 379411,
      "seasonNumber": 2,
      "episodeNumber": 21,
      "absoluteEpisodeNumber": 47,
      "runtime": 25,
      "image": "https://artworks.thetvdb.com/banners/episodes/79525/379411.jpg"
    },
    "22": {
      "episode": "22",
      "length": "25m",
      "airDate": "2008-09-07",
      "title": {
        "en": "Emperor Lelouch"
      },
      "tvdbShowId": 79525,
      "tvdbId": 379412,
      "seasonNumber": 2,
      "episodeNumber": 22,
      "absoluteEpisodeNumber": 48,
      "runtime": 25,
      "image": "https://artworks.thetvdb.com/banners/episodes/79525/379412.jpg"
    },
    "23": {
      "episode": "23",
      "length": "25m",
      "airDate": "2008-09-14",
      "title": {
        "en": "Schneizel`s Guise"
      },
      "tvdbShowId": 79525,
      "tvdbId": 384169,
      "seasonNumber": 2,
      "episodeNumber": 23,
      "absoluteEpisodeNumber": 49,
      "runtime": 25,
      "image": "https://artworks.thetvdb.com/banners/episodes/79525/384169.jpg"
    },
    "24": {
      "episode": "24",
      "length": "25m",
      "airDate": "2008-09-21",
      "title": {
        "en": "The Grip of Damocles"
      },
      "tvdbShowId": 79525,
      "tvdbId": 384170,
      "seasonNumber": 2,
      "episodeNumber": 24,
      "absoluteEpisodeNumber": 50,
      "runtime": 25,
      "image": "https://artworks.thetvdb.com/banners/episodes/79525/384170.jpg"
    },
    "25": {
      "episode": "25",
      "length": "25m",
      "airDate": "2008-09-28",
      "title": {
        "en": "Re;"
      },
      "tvdbShowId": 79525,
      "tvdbId": 384171,
      "seasonNumber": 2,
      "episodeNumber": 25,
      "absoluteEpisodeNumber": 51,
      "runtime": 25,
      "image": "https://artworks.thetvdb.com/banners/episodes/79525/384171.jpg"
    },
    "S1": {
      "episode": "S1",
      "length": "4m",
      "airDate": "2008-08-22",
      "title": {
        "en": "Picture Drama 1"
      },
      "tvdbShowId": 79525,
      "tvdbId": 400421,
      "seasonNumber": 0,
      "episodeNumber": 25,
      "absoluteEpisodeNumber": 0,
      "runtime": 4,
      "image": "https://artworks.thetvdb.com/banners/v4/episode/400421/screencap/60d87717d8464.jpg"
    },
    "S2": {
      "episode": "S2",
      "length": "6m",
      "airDate": "2008-09-26",
      "title": {
        "en": "Picture Drama 2"
      },
      "tvdbShowId": 79525,
      "tvdbId": 1075861,
      "seasonNumber": 0,
      "episodeNumber": 26,
      "absoluteEpisodeNumber": 0,
      "runtime": 6,
      "image": "https://artworks.thetvdb.com/banners/series/79525/episodes/5ea0a455e85d6.jpg"
    },
    "S3": {
      "episode": "S3",
      "length": "5m",
      "airDate": "2008-10-24",
      "title": {
        "en": "Picture Drama 3"
      },
      "tvdbShowId": 79525,
      "tvdbId": 1075871,
      "seasonNumber": 0,
      "episodeNumber": 27,
      "absoluteEpisodeNumber": 0,
      "runtime": 5,
      "image": "https://artworks.thetvdb.com/banners/series/79525/episodes/5ea0a47400c9e.jpg"
    },
    "S4": {
      "episode": "S4",
      "length": "6m",
      "airDate": "2008-11-21",
      "title": {
        "en": "Picture Drama 4"
      },
      "tvdbShowId": 79525,
      "tvdbId": 1075881,
      "seasonNumber": 0,
      "episodeNumber": 28,
      "absoluteEpisodeNumber": 0,
      "runtime": 6,
      "image": "https://artworks.thetvdb.com/banners/series/79525/episodes/5ea0a48fef931.jpg"
    },
    "S5": {
      "episode": "S5",
      "length": "5m",
      "airDate": "2008-12-19",
      "title": {
        "en": "Picture Drama 5"
      },
      "tvdbShowId": 79525,
      "tvdbId": 1075891,
      "seasonNumber": 0,
      "episodeNumber": 30,
      "absoluteEpisodeNumber": 0,
      "runtime": 5,
      "image": "https://artworks.thetvdb.com/banners/series/79525/episodes/5ea0a4a2b6ff0.jpg"
    },
    "S6": {
      "episode": "S6",
      "length": "4m",
      "airDate": "2009-01-23",
      "title": {
        "en": "Picture Drama 6"
      },
      "tvdbShowId": 79525,
      "tvdbId": 1075901,
      "seasonNumber": 0,
      "episodeNumber": 31,
      "absoluteEpisodeNumber": 0,
      "runtime": 4,
      "image": "https://artworks.thetvdb.com/banners/series/79525/episodes/5ea0a4c3b8442.jpg"
    },
    "S7": {
      "episode": "S7",
      "length": "5m",
      "airDate": "2009-02-20",
      "title": {
        "en": "Picture Drama 7"
      },
      "tvdbShowId": 79525,
      "tvdbId": 1075911,
      "seasonNumber": 0,
      "episodeNumber": 32,
      "absoluteEpisodeNumber": 0,
      "runtime": 5,
      "image": "https://artworks.thetvdb.com/banners/series/79525/episodes/5ea0a4e8b10d9.jpg"
    },
    "S8": {
      "episode": "S8",
      "length": "6m",
      "airDate": "2009-03-27",
      "title": {
        "en": "Picture Drama 8"
      },
      "tvdbShowId": 79525,
      "tvdbId": 1075921,
      "seasonNumber": 0,
      "episodeNumber": 33,
      "absoluteEpisodeNumber": 0,
      "runtime": 6,
      "image": "https://artworks.thetvdb.com/banners/series/79525/episodes/5ea0a4fd5888b.jpg"
    },
    "S9": {
      "episode": "S9",
      "length": "5m",
      "airDate": "2009-04-24",
      "title": {
        "en": "Picture Drama 9"
      },
      "tvdbShowId": 79525,
      "tvdbId": 1075931,
      "seasonNumber": 0,
      "episodeNumber": 34,
      "absoluteEpisodeNumber": 0,
      "runtime": 5,
      "image": "https://artworks.thetvdb.com/banners/series/79525/episodes/5ea0a517a33f5.jpg"
    },
    "S10": {
      "episode": "S10",
      "length": "15m",
      "airDate": "2014-03-26",
      "title": {
        "en": "Picture Drama 10"
      },
      "tvdbShowId": 79525,
      "tvdbId": 6667719,
      "seasonNumber": 0,
      "episodeNumber": 29,
      "absoluteEpisodeNumber": 0,
      "runtime": 11,
      "image": "https://artworks.thetvdb.com/banners/series/79525/episodes/5ea0a53e968d7.jpg"
    },
    "S11": {
      "episode": "S11",
      "length": "1m",
      "airDate": "",
      "title": {
        "en": "Omake Flash \"Baba Theater Redux\" Short 1"
      },
      "tvdbShowId": null,
      "tvdbId": null,
      "seasonNumber": null,
      "episodeNumber": null,
      "absoluteEpisodeNumber": null,
      "runtime": null,
      "image": null
    },
    "S12": {
      "episode": "S12",
      "length": "1m",
      "airDate": "",
      "title": {
        "en": "Omake Flash \"Baba Theater Redux\" Short 2"
      },
      "tvdbShowId": null,
      "tvdbId": null,
      "seasonNumber": null,
      "episodeNumber": null,
      "absoluteEpisodeNumber": null,
      "runtime": null,
      "image": null
    },
    "S13": {
      "episode": "S13",
      "length": "1m",
      "airDate": "",
      "title": {
        "en": "Omake Flash \"Baba Theater Redux\" Short 3"
      },
      "tvdbShowId": null,
      "tvdbId": null,
      "seasonNumber": null,
      "episodeNumber": null,
      "absoluteEpisodeNumber": null,
      "runtime": null,
      "image": null
    },
    "S14": {
      "episode": "S14",
      "length": "1m",
      "airDate": "",
      "title": {
        "en": "Omake Flash \"Baba Theater Redux\" Short 4"
      },
      "tvdbShowId": null,
      "tvdbId": null,
      "seasonNumber": null,
      "episodeNumber": null,
      "absoluteEpisodeNumber": null,
      "runtime": null,
      "image": null
    },
    "S15": {
      "episode": "S15",
      "length": "1m",
      "airDate": "",
      "title": {
        "en": "Omake Flash \"Baba Theater Redux\" Short 5"
      },
      "tvdbShowId": null,
      "tvdbId": null,
      "seasonNumber": null,
      "episodeNumber": null,
      "absoluteEpisodeNumber": null,
      "runtime": null,
      "image": null
    },
    "S16": {
      "episode": "S16",
      "length": "1m",
      "airDate": "",
      "title": {
        "en": "Omake Flash \"Baba Theater Redux\" Short 6"
      },
      "tvdbShowId": null,
      "tvdbId": null,
      "seasonNumber": null,
      "episodeNumber": null,
      "absoluteEpisodeNumber": null,
      "runtime": null,
      "image": null
    },
    "S17": {
      "episode": "S17",
      "length": "2m",
      "airDate": "",
      "title": {
        "en": "Omake Flash \"Baba Theater Redux\" Short 7"
      },
      "tvdbShowId": null,
      "tvdbId": null,
      "seasonNumber": null,
      "episodeNumber": null,
      "absoluteEpisodeNumber": null,
      "runtime": null,
      "image": null
    },
    "S18": {
      "episode": "S18",
      "length": "1m",
      "airDate": "",
      "title": {
        "en": "Omake Flash \"Baba Theater Redux\" Short 8"
      },
      "tvdbShowId": null,
      "tvdbId": null,
      "seasonNumber": null,
      "episodeNumber": null,
      "absoluteEpisodeNumber": null,
      "runtime": null,
      "image": null
    },
    "S19": {
      "episode": "S19",
      "length": "3m",
      "airDate": "",
      "title": {
        "en": "Omake Flash \"Baba Theater Redux\" Short 9"
      },
      "tvdbShowId": null,
      "tvdbId": null,
      "seasonNumber": null,
      "episodeNumber": null,
      "absoluteEpisodeNumber": null,
      "runtime": null,
      "image": null
    },
    "S20": {
      "episode": "S20",
      "length": "30m",
      "airDate": "2010-04-23",
      "title": {
        "en": "The Miraculous Birthday"
      },
      "tvdbShowId": 79525,
      "tvdbId": 3404031,
      "seasonNumber": 0,
      "episodeNumber": 36,
      "absoluteEpisodeNumber": 0,
      "runtime": 25,
      "image": "https://artworks.thetvdb.com/banners/episodes/79525/3404031.jpg"
    },
    "S21": {
      "episode": "S21",
      "length": "3m",
      "airDate": "2010-04-23",
      "title": {
        "en": "Code Geass: The Miraculous Birthday Omake Flash \"Baba Theater Redux\" Short"
      },
      "tvdbShowId": null,
      "tvdbId": null,
      "seasonNumber": null,
      "episodeNumber": null,
      "absoluteEpisodeNumber": null,
      "runtime": null,
      "image": null
    },
    "S22": {
      "episode": "S22",
      "length": "5m",
      "airDate": "2013-01-10",
      "title": {
        "en": "Soubou no Oz Picture Drama 1"
      },
      "tvdbShowId": null,
      "tvdbId": null,
      "seasonNumber": null,
      "episodeNumber": null,
      "absoluteEpisodeNumber": null,
      "runtime": null,
      "image": null
    },
    "S23": {
      "episode": "S23",
      "length": "5m",
      "airDate": "2013-01-10",
      "title": {
        "en": "Soubou no Oz Picture Drama 2"
      },
      "tvdbShowId": null,
      "tvdbId": null,
      "seasonNumber": null,
      "episodeNumber": null,
      "absoluteEpisodeNumber": null,
      "runtime": null,
      "image": null
    },
    "S24": {
      "episode": "S24",
      "length": "5m",
      "airDate": "2013-01-10",
      "title": {
        "en": "Soubou no Oz Picture Drama 3"
      },
      "tvdbShowId": null,
      "tvdbId": null,
      "seasonNumber": null,
      "episodeNumber": null,
      "absoluteEpisodeNumber": null,
      "runtime": null,
      "image": null
    },
    "S25": {
      "episode": "S25",
      "length": "5m",
      "airDate": "2013-01-10",
      "title": {
        "en": "Soubou no Oz Picture Drama 4"
      },
      "tvdbShowId": null,
      "tvdbId": null,
      "seasonNumber": null,
      "episodeNumber": null,
      "absoluteEpisodeNumber": null,
      "runtime": null,
      "image": null
    },
    "S26": {
      "episode": "S26",
      "length": "5m",
      "airDate": "2013-01-10",
      "title": {
        "en": "Soubou no Oz Picture Drama 5"
      },
      "tvdbShowId": null,
      "tvdbId": null,
      "seasonNumber": null,
      "episodeNumber": null,
      "absoluteEpisodeNumber": null,
      "runtime": null,
      "image": null
    },
    "OP1": {
      "episode": "OP1",
      "length": "2m",
      "airDate": "2008-04-06",
      "title": {
        "en": "O2 (1-12)"
      },
      "tvdbShowId": null,
      "tvdbId": null,
      "seasonNumber": null,
      "episodeNumber": null,
      "absoluteEpisodeNumber": null,
      "runtime": null,
      "image": null
    },
    "OP2a": {
      "episode": "OP2a",
      "length": "2m",
      "airDate": "2008-07-06",
      "title": {
        "en": "World End (13-25)"
      },
      "tvdbShowId": null,
      "tvdbId": null,
      "seasonNumber": null,
      "episodeNumber": null,
      "absoluteEpisodeNumber": null,
      "runtime": null,
      "image": null
    },
    "OP2b": {
      "episode": "OP2b",
      "length": "2m",
      "airDate": "2008-08-17",
      "title": {
        "en": "World End (13-25)"
      },
      "tvdbShowId": null,
      "tvdbId": null,
      "seasonNumber": null,
      "episodeNumber": null,
      "absoluteEpisodeNumber": null,
      "runtime": null,
      "image": null
    },
    "ED1": {
      "episode": "ED1",
      "length": "2m",
      "airDate": "2008-04-06",
      "title": {
        "en": "Shiawase Neiro (1-12)"
      },
      "tvdbShowId": null,
      "tvdbId": null,
      "seasonNumber": null,
      "episodeNumber": null,
      "absoluteEpisodeNumber": null,
      "runtime": null,
      "image": null
    },
    "ED2a": {
      "episode": "ED2a",
      "length": "2m",
      "airDate": "2008-07-06",
      "title": {
        "en": "Waga Routashi Aku no Hana (13-25)"
      },
      "tvdbShowId": null,
      "tvdbId": null,
      "seasonNumber": null,
      "episodeNumber": null,
      "absoluteEpisodeNumber": null,
      "runtime": null,
      "image": null
    },
    "ED2b": {
      "episode": "ED2b",
      "length": "2m",
      "airDate": "2008-09-28",
      "title": {
        "en": "Waga Routashi Aku no Hana (13-25)"
      },
      "tvdbShowId": null,
      "tvdbId": null,
      "seasonNumber": null,
      "episodeNumber": null,
      "absoluteEpisodeNumber": null,
      "runtime": null,
      "image": null
    },
    "T1": {
      "episode": "T1",
      "length": "1m",
      "airDate": "2007-12-22",
      "title": {
        "en": "DVD Special 21 sec. teaser"
      },
      "tvdbShowId": null,
      "tvdbId": null,
      "seasonNumber": null,
      "episodeNumber": null,
      "absoluteEpisodeNumber": null,
      "runtime": null,
      "image": null
    },
    "T2": {
      "episode": "T2",
      "length": "1m",
      "airDate": "",
      "title": {
        "en": "TV commercial 30 sec. trailer"
      },
      "tvdbShowId": null,
      "tvdbId": null,
      "seasonNumber": null,
      "episodeNumber": null,
      "absoluteEpisodeNumber": null,
      "runtime": null,
      "image": null
    },
    "T3": {
      "episode": "T3",
      "length": "1m",
      "airDate": "",
      "title": {
        "en": "Promo 68 sec. trailer"
      },
      "tvdbShowId": null,
      "tvdbId": null,
      "seasonNumber": null,
      "episodeNumber": null,
      "absoluteEpisodeNumber": null,
      "runtime": null,
      "image": null
    },
    "T4": {
      "episode": "T4",
      "length": "1m",
      "airDate": "",
      "title": {
        "en": "15 second commercial"
      },
      "tvdbShowId": null,
      "tvdbId": null,
      "seasonNumber": null,
      "episodeNumber": null,
      "absoluteEpisodeNumber": null,
      "runtime": null,
      "image": null
    },
    "T5": {
      "episode": "T5",
      "length": "6m",
      "airDate": "",
      "title": {
        "en": "6 minute preview"
      },
      "tvdbShowId": null,
      "tvdbId": null,
      "seasonNumber": null,
      "episodeNumber": null,
      "absoluteEpisodeNumber": null,
      "runtime": null,
      "image": null
    },
    "T6": {
      "episode": "T6",
      "length": "1m",
      "airDate": "2008-06-01",
      "title": {
        "en": "Episode 9-10 Preview"
      },
      "tvdbShowId": null,
      "tvdbId": null,
      "seasonNumber": null,
      "episodeNumber": null,
      "absoluteEpisodeNumber": null,
      "runtime": null,
      "image": null
    },
    "P25": {
      "episode": "P25",
      "length": "25m",
      "airDate": "2008-09-28",
      "title": {
        "en": "Parody of episode 25"
      },
      "tvdbShowId": null,
      "tvdbId": null,
      "seasonNumber": null,
      "episodeNumber": null,
      "absoluteEpisodeNumber": null,
      "runtime": null,
      "image": null
    }
  },
  "meta": {
    "lastFetched": "2026-06-26T22:00:39.628Z",
    "sourcesUsed": [
      "jikan",
      "kitsu",
      "anilist",
      "animeapi.my.id",
      "zenshin"
    ],
    "missingSources": [],
    "dataVersion": 1
  }
}
