{
  "id": 8719,
  "idMal": 8719,
  "mappings": {
    "mal": 8719,
    "anilist": 8719,
    "anidb": 12586,
    "kitsu": 5458,
    "simkl": 640539,
    "tmdb": null,
    "tvdb": null,
    "trakt": null,
    "traktType": null,
    "shikimori": 8719,
    "livechart": null,
    "animeplanet": "donna-donna",
    "anisearch": 6349,
    "notify": "zwCitFmmR"
  },
  "title": {
    "romaji": "Donna Donna",
    "english": null,
    "native": "ドナ ドナ",
    "synonyms": [
      "Minna no Uta",
      "Dona Dona"
    ]
  },
  "type": "Music",
  "source": "Music",
  "status": "Finished Airing",
  "airing": false,
  "episodeCount": 1,
  "episodeLength": 2,
  "aired": {
    "from": "1966-02-11T00:00:00+00:00",
    "to": "1966-02-01"
  },
  "season": null,
  "year": null,
  "broadcast": {
    "day": null,
    "time": null,
    "timezone": null
  },
  "nextAiringEpisode": null,
  "rating": "G - All Ages",
  "score": {
    "malScore": 5.11,
    "anilistScore": 4.2,
    "kitsuRating": null
  },
  "genres": [
    "Slice of Life",
    "Music",
    "Kids"
  ],
  "studios": [],
  "producers": [
    "NHK"
  ],
  "images": {
    "poster": "https://cdn.myanimelist.net/images/anime/4/24063l.jpg",
    "banner": null,
    "color": null
  },
  "trailer": null,
  "synopsis": "A calf goes to a new home while memories of happiness flash by.\n\nThis is a 1966 Japanese version of an old 1938 Yiddish folk song that was featured in NHK's Minna no Uta.",
  "sequence": [],
  "episodes": {
    "1": {
      "episode": "1",
      "length": "3m",
      "airDate": "",
      "title": {
        "en": "Episode 1"
      },
      "tvdbShowId": null,
      "tvdbId": null,
      "seasonNumber": null,
      "episodeNumber": 1,
      "absoluteEpisodeNumber": null,
      "runtime": null,
      "image": null
    }
  },
  "meta": {
    "lastFetched": "2026-06-27T08:46:09.032Z",
    "sourcesUsed": [
      "jikan",
      "kitsu",
      "anilist",
      "animeapi.my.id",
      "zenshin"
    ],
    "missingSources": [],
    "dataVersion": 1
  }
}
