{
  "id": 8792,
  "idMal": 8792,
  "mappings": {
    "mal": 8792,
    "anilist": 8792,
    "anidb": null,
    "kitsu": 5496,
    "simkl": null,
    "tmdb": null,
    "tvdb": null,
    "trakt": null,
    "traktType": null,
    "shikimori": 8792,
    "livechart": 5584,
    "animeplanet": "madobe-nanami-no-windows-7-de-pc-jisaku-ouen-commercial",
    "anisearch": 6938,
    "notify": "mfiZtFmmg"
  },
  "title": {
    "romaji": "Madobe Nanami no Windows 7 de PC Jisaku Ouen Commercial!!",
    "english": null,
    "native": "窓辺ななみのWindows 7でPC自作応援コマーシャルっ!!",
    "synonyms": [
      "Madobe Nanami's Homemade Windows 7 PC Cheerleading Commercial!!"
    ]
  },
  "type": "CM",
  "source": "Other",
  "status": "Finished Airing",
  "airing": false,
  "episodeCount": 1,
  "episodeLength": 1,
  "aired": {
    "from": "2010-05-09T00:00:00+00:00",
    "to": "2010-05-09"
  },
  "season": "spring",
  "year": 2010,
  "broadcast": {
    "day": null,
    "time": null,
    "timezone": null
  },
  "nextAiringEpisode": null,
  "rating": "G - All Ages",
  "score": {
    "malScore": 6.21,
    "anilistScore": 5.8,
    "kitsuRating": 6.18
  },
  "genres": [
    "Comedy"
  ],
  "studios": [
    "Rising Force"
  ],
  "producers": [],
  "images": {
    "poster": "https://cdn.myanimelist.net/images/anime/1387/147466l.jpg",
    "banner": "https://s4.anilist.co/file/anilistcdn/media/anime/banner/8792-PJvAKDSHijrg.jpg",
    "color": "#0d78e4"
  },
  "trailer": null,
  "synopsis": "Madobe Nanami is a computer store employee who instructs customers on how to magically assemble their PCs.  She also shows them some of the features of Windows 7.",
  "sequence": [],
  "episodes": {},
  "meta": {
    "lastFetched": "2026-06-27T08:47:36.221Z",
    "sourcesUsed": [
      "jikan",
      "kitsu",
      "anilist",
      "animeapi.my.id",
      "zenshin"
    ],
    "missingSources": [],
    "dataVersion": 1
  }
}
