{
  "id": 44149,
  "idMal": 44149,
  "mappings": {
    "mal": 44149,
    "anilist": 129596,
    "anidb": null,
    "kitsu": 44057,
    "simkl": null,
    "tmdb": null,
    "tvdb": null,
    "trakt": null,
    "traktType": null,
    "shikimori": 44149,
    "livechart": null,
    "animeplanet": "seer-7th-season",
    "anisearch": null,
    "notify": null
  },
  "title": {
    "romaji": "Seer 7",
    "english": null,
    "native": "赛尔号 第七季",
    "synonyms": [
      "Seer Seventh Season",
      "赛尔号第7季：宇宙之眼"
    ]
  },
  "type": "TV",
  "source": "Game",
  "status": "Finished Airing",
  "airing": false,
  "episodeCount": 30,
  "episodeLength": null,
  "aired": {
    "from": "2016-06-03T00:00:00+00:00",
    "to": "2016-09-17T00:00:00+00:00"
  },
  "season": "summer",
  "year": 2016,
  "broadcast": {
    "day": null,
    "time": null,
    "timezone": null
  },
  "nextAiringEpisode": null,
  "rating": "PG - Children",
  "score": {
    "malScore": null,
    "anilistScore": null,
    "kitsuRating": null
  },
  "genres": [
    "Adventure",
    "Fantasy",
    "Sci-Fi"
  ],
  "studios": [
    "Taomee"
  ],
  "producers": [],
  "images": {
    "poster": "https://cdn.myanimelist.net/images/anime/1724/117999l.jpg",
    "banner": null,
    "color": "#f1d61a"
  },
  "trailer": null,
  "synopsis": null,
  "sequence": [
    {
      "malId": 44148,
      "title": {
        "romaji": "Seer 6",
        "english": null,
        "native": "赛尔号 第六季"
      },
      "image": "https://s4.anilist.co/file/anilistcdn/media/anime/cover/medium/b129594-NRb4Fgdrmmtc.jpg",
      "format": "TV_SHORT",
      "episodes": 30,
      "seasonYear": null,
      "relationType": "PREQUEL"
    },
    {
      "malId": 44151,
      "title": {
        "romaji": "Seer 8",
        "english": null,
        "native": "赛尔号 第八季"
      },
      "image": "https://s4.anilist.co/file/anilistcdn/media/anime/cover/medium/b129597-KLGJFdoMsGxZ.jpg",
      "format": "TV",
      "episodes": 30,
      "seasonYear": null,
      "relationType": "SEQUEL"
    }
  ],
  "episodes": {},
  "meta": {
    "lastFetched": "2026-06-29T21:06:47.972Z",
    "sourcesUsed": [
      "jikan",
      "kitsu",
      "anilist",
      "animeapi.my.id",
      "zenshin"
    ],
    "missingSources": [],
    "dataVersion": 1
  }
}
