{
  "id": 1014,
  "idMal": 1014,
  "mappings": {
    "mal": 1014,
    "anilist": 1014,
    "anidb": 7300,
    "kitsu": 904,
    "simkl": 36205,
    "tmdb": 22758,
    "tvdb": null,
    "trakt": null,
    "traktType": null,
    "shikimori": 1014,
    "livechart": 11280,
    "animeplanet": "a-little-snow-fairy-sugar-summer-specials",
    "anisearch": 3554,
    "notify": "W001cKmig"
  },
  "title": {
    "romaji": "Chicchana Yukitsukai Sugar Tokubetsu-hen",
    "english": "Sugar: A Little Snow Fairy Summer Special",
    "native": "ちっちゃな雪使いシュガー特別編",
    "synonyms": [
      "Chiccha na Yukitsukai Sugar Special",
      "Chiccha na Yukitsukai Sugar Tokubetsu Hen",
      "Chicchana Yukitsukai Sugar Specials"
    ]
  },
  "type": "TV Special",
  "source": "Original",
  "status": "Finished Airing",
  "airing": false,
  "episodeCount": 2,
  "episodeLength": 24,
  "aired": {
    "from": "2003-08-21T00:00:00+00:00",
    "to": "2003-08-28T00:00:00+00:00"
  },
  "season": "summer",
  "year": 2003,
  "broadcast": {
    "day": null,
    "time": null,
    "timezone": null
  },
  "nextAiringEpisode": null,
  "rating": "G - All Ages",
  "score": {
    "malScore": 7.03,
    "malScoredBy": 2528,
    "malRank": 4625,
    "malPopularity": 8995,
    "malMembers": 5977,
    "malFavorites": 6,
    "anilistScore": 6.4,
    "anilistPopularity": 1164,
    "anilistFavourites": 6,
    "anilistTrending": 0,
    "kitsuRating": 6.93
  },
  "genres": [
    "Comedy",
    "Fantasy",
    "Slice of Life",
    "Magic",
    "Earth",
    "Germany",
    "Contemporary Fantasy",
    "Performance",
    "Europe",
    "The Arts",
    "Present"
  ],
  "studios": [
    "J.C.Staff"
  ],
  "producers": [
    "Kadokawa Shoten",
    "Broccoli",
    "TBS",
    "Pioneer LDC"
  ],
  "images": {
    "poster": "https://cdn.myanimelist.net/images/anime/12/23190l.jpg",
    "banner": "https://media.kitsu.app/anime/cover_images/904/original.jpg",
    "color": "#febb0d"
  },
  "trailer": null,
  "synopsis": "When Saga—now 15 years old—arrives at her home after a day of errands, her grandmother Regina discovers an old dress in the attic. At this point, Saga recalls the time her elementary class participated in a play titled \"Princess and Fairy.\" She volunteered to play the role of the Princess while her rival Greta played the evil witch. The production of the school play reminded Sugar and the other fairies of the time \"The Bear Pianist\" played in the town not too long ago.",
  "sequence": [
    {
      "malId": 831,
      "title": {
        "romaji": "Chicchana Yukitsukai Sugar",
        "english": "A Little Snow Fairy Sugar",
        "native": "ちっちゃな雪使いシュガー"
      },
      "image": "https://s4.anilist.co/file/anilistcdn/media/anime/cover/medium/831.jpg",
      "format": "TV",
      "episodes": 24,
      "seasonYear": 2001,
      "relationType": "PREQUEL"
    }
  ],
  "episodes": {
    "1": {
      "episode": "1",
      "length": "25m",
      "airDate": "2003-08-22",
      "title": {
        "en": "What`s in the Heart (Part One)"
      },
      "tvdbShowId": null,
      "tvdbId": null,
      "seasonNumber": null,
      "episodeNumber": 1,
      "absoluteEpisodeNumber": null,
      "runtime": null,
      "image": null
    },
    "2": {
      "episode": "2",
      "length": "25m",
      "airDate": "2003-08-29",
      "title": {
        "en": "What`s in the Heart (Part Two)"
      },
      "tvdbShowId": null,
      "tvdbId": null,
      "seasonNumber": null,
      "episodeNumber": 2,
      "absoluteEpisodeNumber": null,
      "runtime": null,
      "image": null
    },
    "ED1": {
      "episode": "ED1",
      "length": "2m",
      "airDate": "2003-08-22",
      "title": {
        "en": "Kokoro no Piano (1-2)"
      },
      "tvdbShowId": null,
      "tvdbId": null,
      "seasonNumber": null,
      "episodeNumber": null,
      "absoluteEpisodeNumber": null,
      "runtime": null,
      "image": null
    }
  },
  "meta": {
    "lastFetched": "2026-06-26T12:55:09.735Z",
    "sourcesUsed": [
      "jikan",
      "kitsu",
      "anilist",
      "animeapi.my.id",
      "zenshin",
      "simkl"
    ],
    "missingSources": [],
    "dataVersion": 1
  }
}
