{
  "id": 40690,
  "idMal": 40690,
  "mappings": {
    "mal": 40690,
    "anilist": null,
    "anidb": null,
    "kitsu": 48347,
    "simkl": null,
    "tmdb": null,
    "tvdb": null,
    "trakt": null,
    "traktType": null,
    "shikimori": 40690,
    "livechart": null,
    "animeplanet": "crazy-b-crazy-roulette",
    "anisearch": null,
    "notify": null
  },
  "title": {
    "romaji": "Crazy Roulette",
    "english": "Crazy Roulette",
    "native": "あんさんぶるスターズ！！ Music MV vol.4 「Crazy Roulette」",
    "synonyms": [
      "Ensemble Stars!! Unit Song CD Crazy:B"
    ]
  },
  "type": "Music",
  "source": "Game",
  "status": "Finished Airing",
  "airing": false,
  "episodeCount": 1,
  "episodeLength": 2,
  "aired": {
    "from": "2019-11-09T00:00:00+00:00",
    "to": "2019-11-09"
  },
  "season": null,
  "year": null,
  "broadcast": {
    "day": null,
    "time": null,
    "timezone": null
  },
  "nextAiringEpisode": null,
  "rating": "PG-13 - Teens 13 or older",
  "score": {
    "malScore": 6.82,
    "anilistScore": null,
    "kitsuRating": null
  },
  "genres": [
    "Music",
    "Idol"
  ],
  "studios": [
    "Happy Elements"
  ],
  "producers": [],
  "images": {
    "poster": "https://cdn.myanimelist.net/images/anime/1189/113605l.jpg",
    "banner": null,
    "color": null
  },
  "trailer": null,
  "synopsis": "A music video for one of Ensemble Star's newest units, Crazy:B, of their debut song Crazy Roulette.",
  "sequence": [],
  "episodes": {},
  "meta": {
    "lastFetched": "2026-06-29T08:56:16.005Z",
    "sourcesUsed": [
      "jikan",
      "kitsu",
      "animeapi.my.id"
    ],
    "missingSources": [
      "anilist",
      "zenshin (no AniList id resolved)"
    ],
    "dataVersion": 1
  }
}
