{
  "id": 56990,
  "idMal": 56990,
  "mappings": {
    "mal": 56990,
    "anilist": null,
    "anidb": null,
    "kitsu": 48804,
    "simkl": null,
    "tmdb": null,
    "tvdb": null,
    "trakt": null,
    "traktType": null,
    "shikimori": 56990,
    "livechart": null,
    "animeplanet": "dinocore-season-3",
    "anisearch": 15310,
    "notify": null
  },
  "title": {
    "romaji": "DinoCore Season 3",
    "english": null,
    "native": "다이노코어 시즌 3",
    "synonyms": []
  },
  "type": "TV",
  "source": "Other",
  "status": "Finished Airing",
  "airing": false,
  "episodeCount": 13,
  "episodeLength": 11,
  "aired": {
    "from": "2017-10-07T00:00:00+00:00",
    "to": "2017-12-30T00:00:00+00:00"
  },
  "season": "fall",
  "year": 2017,
  "broadcast": {
    "day": null,
    "time": null,
    "timezone": null
  },
  "nextAiringEpisode": null,
  "rating": "PG - Children",
  "score": {
    "malScore": null,
    "anilistScore": null,
    "kitsuRating": null
  },
  "genres": [
    "Action",
    "Kids",
    "Mecha"
  ],
  "studios": [],
  "producers": [],
  "images": {
    "poster": "https://cdn.myanimelist.net/images/anime/1278/139301l.jpg",
    "banner": null,
    "color": null
  },
  "trailer": null,
  "synopsis": null,
  "sequence": [],
  "episodes": {},
  "meta": {
    "lastFetched": "2026-06-30T19:17:38.821Z",
    "sourcesUsed": [
      "jikan",
      "kitsu",
      "animeapi.my.id",
      "zenshin"
    ],
    "missingSources": [
      "anilist (not in ID mappings)",
      "episodes (no data from Zenshin or Jikan)"
    ],
    "dataVersion": 1
  }
}
