{
  "id": 57123,
  "idMal": 57123,
  "mappings": {
    "mal": 57123,
    "anilist": 188816,
    "anidb": null,
    "kitsu": null,
    "simkl": null,
    "tmdb": null,
    "tvdb": null,
    "trakt": null,
    "traktType": null,
    "shikimori": 57123,
    "livechart": null,
    "animeplanet": null,
    "anisearch": null,
    "notify": null
  },
  "title": {
    "romaji": "Choegangjeonsa Mini Teukgongdae: Yeongungui Tansaeng",
    "english": "Mini Force: New Heroes Rise",
    "native": "최강전사 미니특공대: 영웅의 탄생",
    "synonyms": []
  },
  "type": "Movie",
  "source": "Original",
  "status": "Finished Airing",
  "airing": false,
  "episodeCount": 1,
  "episodeLength": null,
  "aired": {
    "from": "2016-02-04T00:00:00+00:00",
    "to": null
  },
  "season": null,
  "year": null,
  "broadcast": {
    "day": null,
    "time": null,
    "timezone": null
  },
  "nextAiringEpisode": null,
  "rating": "PG - Children",
  "score": {
    "malScore": null,
    "anilistScore": null,
    "kitsuRating": null
  },
  "genres": [
    "Action",
    "Mecha"
  ],
  "studios": [
    "SAMG Entertainment",
    "SAMG Animation"
  ],
  "producers": [],
  "images": {
    "poster": "https://cdn.myanimelist.net/images/anime/1014/139585l.jpg",
    "banner": null,
    "color": "#35d6f1"
  },
  "trailer": null,
  "synopsis": null,
  "sequence": [
    {
      "malId": 35799,
      "title": {
        "romaji": "Choegangjeonsa Mini Teukgongdae",
        "english": "Mini Force",
        "native": "최강전사 미니특공대"
      },
      "image": "https://s4.anilist.co/file/anilistcdn/media/anime/cover/medium/b188813-i2viaFA9BTLf.png",
      "format": "TV_SHORT",
      "episodes": 26,
      "seasonYear": null,
      "relationType": "PARENT"
    }
  ],
  "episodes": {},
  "meta": {
    "lastFetched": "2026-06-30T19:21:27.815Z",
    "sourcesUsed": [
      "jikan",
      "kitsu",
      "anilist",
      "animeapi.my.id",
      "zenshin"
    ],
    "missingSources": [],
    "dataVersion": 1
  }
}
