{
  "id": 41146,
  "idMal": 41146,
  "mappings": {
    "mal": 41146,
    "anilist": 114926,
    "anidb": 15372,
    "kitsu": 42986,
    "simkl": 1249671,
    "tmdb": 93495,
    "tvdb": null,
    "trakt": null,
    "traktType": null,
    "shikimori": 41146,
    "livechart": 10082,
    "animeplanet": "kandagawa-jet-girls-ova",
    "anisearch": 14910,
    "notify": "1AcZi2UWR"
  },
  "title": {
    "romaji": "Kandagawa JET GIRLS OVA",
    "english": "Kandagawa Jet Girls OVA",
    "native": "神田川 JET GIRLS OVA",
    "synonyms": [
      "Kandagawa Jet Girls OVA"
    ]
  },
  "type": "OVA",
  "source": "Mixed media",
  "status": "Finished Airing",
  "airing": false,
  "episodeCount": 1,
  "episodeLength": 22,
  "aired": {
    "from": "2020-01-24T00:00:00+00:00",
    "to": "2020-01-24"
  },
  "season": "winter",
  "year": 2020,
  "broadcast": {
    "day": null,
    "time": null,
    "timezone": null
  },
  "nextAiringEpisode": null,
  "rating": "PG-13 - Teens 13 or older",
  "score": {
    "malScore": 5.63,
    "anilistScore": 5.1,
    "kitsuRating": 6.09
  },
  "genres": [
    "Sci-Fi",
    "Ecchi",
    "Sports"
  ],
  "studios": [
    "TNK"
  ],
  "producers": [],
  "images": {
    "poster": "https://cdn.myanimelist.net/images/anime/1643/105654l.jpg",
    "banner": "https://media.kitsu.app/anime/42986/cover_image/95358cb6acead3476761d3b90aee069c.jpg",
    "color": "#1aa1d6"
  },
  "trailer": null,
  "synopsis": "OVA which was released as a tie-in to the Kandagawa Jet Girls  video game for PlayStation 4.",
  "sequence": [
    {
      "malId": 40196,
      "title": {
        "romaji": "Kandagawa JET GIRLS",
        "english": "Kandagawa Jet Girls",
        "native": "神田川JET GIRLS"
      },
      "image": "https://s4.anilist.co/file/anilistcdn/media/anime/cover/medium/bx110810-dJEpyDWfzbfX.jpg",
      "format": "TV",
      "episodes": 12,
      "seasonYear": 2019,
      "relationType": "PREQUEL"
    }
  ],
  "episodes": {
    "1": {
      "episode": "1",
      "length": "25m",
      "airDate": "2020-01-16",
      "title": {
        "en": "OVA"
      },
      "tvdbShowId": 369146,
      "tvdbId": 7554588,
      "seasonNumber": 0,
      "episodeNumber": 2,
      "absoluteEpisodeNumber": 14,
      "runtime": 25,
      "image": "https://artworks.thetvdb.com/banners/series/369146/episodes/62061437.jpg"
    }
  },
  "meta": {
    "lastFetched": "2026-06-29T09:17:40.502Z",
    "sourcesUsed": [
      "jikan",
      "kitsu",
      "anilist",
      "animeapi.my.id",
      "zenshin"
    ],
    "missingSources": [],
    "dataVersion": 1
  }
}
